verilog/exercises/3.sv
module ex3 (
	input logic [3:0] a,
	output logic y
);
	assign y = ^a;
endmodule

book/verilog/exercises/4.sv
module tb4 ();
	logic [3:0] a;
	logic y;

	ex3 exercise(a, y);

	initial begin
		$dumpfile("ex4.vcd");
		$dumpvars(0, tb4);

		#00 a = 4'b0000;
		#10 a = 4'b0001;
		#20 a = 4'b0010;
		#30 a = 4'b0011;
		#40 a = 4'b0100;
		#50 a = 4'b0101;
		#60 a = 4'b0110;
		#70 a = 4'b0111;
		#80 a = 4'b1000;
		#90 a = 4'b1001;
		#100 a = 4'b1010;
		#110 a = 4'b1011;
		#120 a = 4'b1100;
		#130 a = 4'b1101;
		#140 a = 4'b1110;
		#150 a = 4'b1111;
	end


	
endmodule

verilog/exercises/ex4.vcd
$date
	Mon Dec 26 10:55:50 2022
$end
$version
	Icarus Verilog
$end
$timescale
	1s
$end
$scope module tb4 $end
$var wire 1 ! y $end
$var reg 4 " a [3:0] $end
$scope module exercise $end
$var wire 4 # a [3:0] $end
$var wire 1 ! y $end
$upscope $end
$upscope $end
$enddefinitions $end
$comment Show the parameter values. $end
$dumpall
$end
#0
$dumpvars
b0 #
b0 "
0!
$end
#10
1!
b1 "
b1 #
#30
b10 "
b10 #
#60
0!
b11 "
b11 #
#100
1!
b100 "
b100 #
#150
0!
b101 "
b101 #
#210
b110 "
b110 #
#280
1!
b111 "
b111 #
#360
b1000 "
b1000 #
#450
0!
b1001 "
b1001 #
#550
b1010 "
b1010 #
#660
1!
b1011 "
b1011 #
#780
0!
b1100 "
b1100 #
#910
1!
b1101 "
b1101 #
#1050
b1110 "
b1110 #
#1200
0!
b1111 "
b1111 #
