book/verilog/exercises/6.sv
module display (
	input logic [3:0] number,
	output logic [6:0] display
);

	always_comb 
		case (number)
			4'h0:  display = 7'b1111111;
			4'h1:  display = 7'b1111000;
			4'h2:  display = 7'b1101101;
			4'h3:  display = 7'b1111001;
			4'h4:  display = 7'b0110011;
			4'h5:  display = 7'b1011011;
			4'h6:  display = 7'b1011111;
			4'h7:  display = 7'b1110000;
			4'h8:  display = 7'b1111111;
			4'h9:  display = 7'b1110011;
			4'ha:  display = 7'b1110111;
			4'hb:  display = 7'b0011111;
			4'hc:  display = 7'b1001110;
			4'hd:  display = 7'b0111101;
			4'he:  display = 7'b1001111;
			4'hf:  display = 7'b1000111;
			default: display = 7'b000_0000; 
		endcase
	
endmodule

book/verilog/exercises/7.sv
module tb7 ();
	logic [3:0] number;
	logic [6:0] display;


	display exercise(number, display);

	initial begin
		$dumpfile("7.vcd");
		$dumpvars(0, tb7);

		#0 number = 4'h0;
		#1 number = 4'h1;
		#2 number = 4'h2;
		#3 number = 4'h3;
		#4 number = 4'h4;
		#5 number = 4'h5;
		#6 number = 4'h6;
		#7 number = 4'h7;
		#8 number = 4'h8;
		#9 number = 4'h9;
		#10 number = 4'ha;
		#11 number = 4'hb;
		#12 number = 4'hc;
		#13 number = 4'hd;
		#14 number = 4'he;
		#15 number = 4'hf;
	end
	
endmodule

book/verilog/exercises/7.vcd
$date
	Mon Dec 26 11:52:00 2022
$end
$version
	Icarus Verilog
$end
$timescale
	1s
$end
$scope module tb7 $end
$var wire 7 ! display [6:0] $end
$var reg 4 " number [3:0] $end
$scope module exercise $end
$var wire 4 # number [3:0] $end
$var reg 7 $ display [6:0] $end
$upscope $end
$upscope $end
$enddefinitions $end
$comment Show the parameter values. $end
$dumpall
$end
#0
$dumpvars
b1111111 $
b0 #
b0 "
b1111111 !
$end
#1
b1111000 !
b1111000 $
b1 "
b1 #
#3
b1101101 !
b1101101 $
b10 "
b10 #
#6
b1111001 !
b1111001 $
b11 "
b11 #
#10
b110011 !
b110011 $
b100 "
b100 #
#15
b1011011 !
b1011011 $
b101 "
b101 #
#21
b1011111 !
b1011111 $
b110 "
b110 #
#28
b1110000 !
b1110000 $
b111 "
b111 #
#36
b1111111 !
b1111111 $
b1000 "
b1000 #
#45
b1110011 !
b1110011 $
b1001 "
b1001 #
#55
b1110111 !
b1110111 $
b1010 "
b1010 #
#66
b11111 !
b11111 $
b1011 "
b1011 #
#78
b1001110 !
b1001110 $
b1100 "
b1100 #
#91
b111101 !
b111101 $
b1101 "
b1101 #
#105
b1001111 !
b1001111 $
b1110 "
b1110 #
#120
b1000111 !
b1000111 $
b1111 "
b1111 #
